dvadmin_celery/__init__.py
dvadmin_celery/admin.py
dvadmin_celery/apps.py
dvadmin_celery/settings.py
dvadmin_celery/tasks.py
dvadmin_celery/urls.py
dvadmin_celery/fixtures/__init__.py
dvadmin_celery/fixtures/init_menu.json
dvadmin_celery/fixtures/initialize.py
dvadmin_celery/views/__init__.py
dvadmin_celery/views/crontab_schedule.py
dvadmin_celery/views/interval_schedule.py
dvadmin_celery/views/periodic_task.py
dvadmin_celery/views/task.py
dvadmin_celery/views/task_detail.py
dadmin_celery-1.0.3.dist-info/LICENSE
dadmin_celery-1.0.3.dist-info/METADATA
dadmin_celery-1.0.3.dist-info/WHEEL
dadmin_celery-1.0.3.dist-info/top_level.txt
dadmin_celery-1.0.3.dist-info/RECORD
