Metadata-Version: 2.1
Name: dadmin-celery
Version: 1.0.3
Summary: 适用于 django-vue-admin 的celery异步插件
Home-page: https://gitee.com/zouxingshun/dvadmin-celery
Author: zouxs
Author-email: liqiang@django-vue-admin.com
Classifier: Programming Language :: Python :: 3
Classifier: License :: OSI Approved :: MIT License
Classifier: Operating System :: OS Independent
Requires-Python: >=3.7, <4
License-File: LICENSE
Requires-Dist: django-celery-beat >=2.5.0
Requires-Dist: tenant-schemas-celery >=2.2.0
Requires-Dist: django-redis >=5.2.0
Requires-Dist: django-celery-results >=2.5.1
